{"Constituencies":[{"Constituency_Name":"Musselburgh","Constituency_Number":"S13002908","Directory":"S13002908","countInfo":{"Valid_Poll":"7608","Number_Of_Seats":"4","Total_Poll":"7747","Voting_Age_Pop":"15874","Quota":1522,"Constituency_Name":"Musselburgh","Constituency_Number":"S13002908","Total_Electorate":"15874","Spoiled":139}},{"Constituency_Name":"Preston, Seton and Gosford","Constituency_Number":"S13002909","Directory":"S13002909","countInfo":{"Valid_Poll":"7397","Number_Of_Seats":"4","Total_Poll":"7575","Voting_Age_Pop":"14702","Quota":1480,"Constituency_Name":"Preston, Seton and Gosford","Constituency_Number":"S13002909","Total_Electorate":"14702","Spoiled":178}},{"Constituency_Name":"Tranent, Wallyford and Macmerry","Constituency_Number":"S13002910","Directory":"S13002910","countInfo":{"Valid_Poll":"6279","Number_Of_Seats":"4","Total_Poll":"6406","Voting_Age_Pop":"14699","Quota":1256,"Constituency_Name":"Tranent, Wallyford and Macmerry","Constituency_Number":"S13002910","Total_Electorate":"14699","Spoiled":127}},{"Constituency_Name":"North Berwick Coastal","Constituency_Number":"S13002911","Directory":"S13002911","countInfo":{"Valid_Poll":"6270","Number_Of_Seats":"3","Total_Poll":"6384","Voting_Age_Pop":"10752","Quota":1568,"Constituency_Name":"North Berwick Coastal","Constituency_Number":"S13002911","Total_Electorate":"10752","Spoiled":114}},{"Constituency_Name":"Haddington and Lammermuir","Constituency_Number":"S13002912","Directory":"S13002912","countInfo":{"Valid_Poll":"7790","Number_Of_Seats":"4","Total_Poll":"7898","Voting_Age_Pop":"14095","Quota":1559,"Constituency_Name":"Haddington and Lammermuir","Constituency_Number":"S13002912","Total_Electorate":"14095","Spoiled":108}},{"Constituency_Name":"Dunbar and East Linton","Constituency_Number":"S13002913","Directory":"S13002913","countInfo":{"Valid_Poll":"6141","Number_Of_Seats":"3","Total_Poll":"6184","Voting_Age_Pop":"10955","Quota":1536,"Constituency_Name":"Dunbar and East Linton","Constituency_Number":"S13002913","Total_Electorate":"10955","Spoiled":43}}]}