{"Constituencies":[{"Constituency_Name":"Trossachs and Teith","Constituency_Number":"S13003115","Directory":"S13003115","countInfo":{"Valid_Poll":"5314","Number_Of_Seats":"3","Total_Poll":"5432","Voting_Age_Pop":"9147","Quota":1329,"Constituency_Name":"Trossachs and Teith","Constituency_Number":"S13003115","Total_Electorate":"9147","Spoiled":118}},{"Constituency_Name":"Forth and Endrick","Constituency_Number":"S13003116","Directory":"S13003116","countInfo":{"Valid_Poll":"6213","Number_Of_Seats":"3","Total_Poll":"6328","Voting_Age_Pop":"10405","Quota":1554,"Constituency_Name":"Forth and Endrick","Constituency_Number":"S13003116","Total_Electorate":"10405","Spoiled":115}},{"Constituency_Name":"Dunblane and Bridge of Allan","Constituency_Number":"S13003117","Directory":"S13003117","countInfo":{"Valid_Poll":"6977","Number_Of_Seats":"4","Total_Poll":"7100","Voting_Age_Pop":"11484","Quota":1396,"Constituency_Name":"Dunblane and Bridge of Allan","Constituency_Number":"S13003117","Total_Electorate":"11484","Spoiled":123}},{"Constituency_Name":"Stirling North","Constituency_Number":"S13003118","Directory":"S13003118","countInfo":{"Valid_Poll":"4631","Number_Of_Seats":"4","Total_Poll":"4755","Voting_Age_Pop":"10512","Quota":927,"Constituency_Name":"Stirling North","Constituency_Number":"S13003118","Total_Electorate":"10512","Spoiled":124}},{"Constituency_Name":"Stirling West","Constituency_Number":"S13003119","Directory":"S13003119","countInfo":{"Valid_Poll":"5251","Number_Of_Seats":"3","Total_Poll":"5325","Voting_Age_Pop":"9637","Quota":1313,"Constituency_Name":"Stirling West","Constituency_Number":"S13003119","Total_Electorate":"9637","Spoiled":74}},{"Constituency_Name":"Stirling East","Constituency_Number":"S13003120","Directory":"S13003120","countInfo":{"Valid_Poll":"3786","Number_Of_Seats":"3","Total_Poll":"3879","Voting_Age_Pop":"8479","Quota":947,"Constituency_Name":"Stirling East","Constituency_Number":"S13003120","Total_Electorate":"8479","Spoiled":93}},{"Constituency_Name":"Bannockburn","Constituency_Number":"S13003121","Directory":"S13003121","countInfo":{"Valid_Poll":"3503","Number_Of_Seats":"3","Total_Poll":"3627","Voting_Age_Pop":"8672","Quota":876,"Constituency_Name":"Bannockburn","Constituency_Number":"S13003121","Total_Electorate":"8672","Spoiled":124}}]}